ptyrodactyl/__init__.py
ptyrodactyl/invert/__init__.py
ptyrodactyl/invert/phase_recon.py
ptyrodactyl/invert/py.typed
ptyrodactyl/py.typed
ptyrodactyl/simul/__init__.py
ptyrodactyl/simul/atom_potentials.py
ptyrodactyl/simul/geometry.py
ptyrodactyl/simul/luggage/Kirkland_Potentials.csv
ptyrodactyl/simul/luggage/atom_numbers.json
ptyrodactyl/simul/parallelized.py
ptyrodactyl/simul/preprocessing.py
ptyrodactyl/simul/py.typed
ptyrodactyl/simul/simulations.py
ptyrodactyl/tools/__init__.py
ptyrodactyl/tools/electron_types.py
ptyrodactyl/tools/factory.py
ptyrodactyl/tools/loss_functions.py
ptyrodactyl/tools/optimizers.py
ptyrodactyl/tools/parallel.py
ptyrodactyl/tools/py.typed
ptyrodactyl/workflows/__init__.py
ptyrodactyl/workflows/py.typed
ptyrodactyl/workflows/stem_4d.py
ptyrodactyl-2025.9.21.dist-info/WHEEL
ptyrodactyl-2025.9.21.dist-info/METADATA
ptyrodactyl-2025.9.21.dist-info/RECORD
