Metadata-Version: 2.3
Name: ptyrodactyl
Version: 2025.9.21
Summary: Ptychography through differentiable programming in JAX
Keywords: electron microscopy,optical microscopy,4D-STEM,JAX,ptychography,differentiable programming
Author: Debangshu Mukherjee
Author-email: Debangshu Mukherjee <mukherjeed@ornl.gov>
License: MIT License
Classifier: Programming Language :: Python :: 3.11
Classifier: Programming Language :: Python :: 3.12
Classifier: Programming Language :: Python :: 3.13
Classifier: License :: OSI Approved :: MIT License
Classifier: Operating System :: OS Independent
Classifier: Typing :: Typed
Classifier: Topic :: Scientific/Engineering :: Image Processing
Requires-Dist: numpy>=1.13.0
Requires-Dist: scipy>=1.0.0
Requires-Dist: matplotlib>=2.2.0
Requires-Dist: matplotlib-scalebar>=0.5.0
Requires-Dist: tqdm>=4.66.0
Requires-Dist: jaxtyping>=0.2.21
Requires-Dist: chex>=0.1.85
Requires-Dist: optax>=0.1.8
Requires-Dist: pytest>=8.0.0
Requires-Dist: beartype>=0.19.0
Requires-Dist: jax>=0.7.0 ; sys_platform == 'win64'
Requires-Dist: jax>=0.7.0 ; sys_platform == 'darwin'
Requires-Dist: jax>=0.7.0 ; sys_platform == 'linux'
Requires-Dist: pytest-cov>=6.2.1
Requires-Dist: jupyterlab>=4.4.5
Requires-Dist: jupyter>=1.1.1
Requires-Dist: ipykernel>=6.29.5
Requires-Dist: jax[cuda12]>=0.7.0 ; platform_machine == 'x86_64' and sys_platform == 'linux' and extra == 'cuda'
Requires-Dist: nvidia-cudnn-cu12>=9.5.0 ; platform_machine == 'x86_64' and sys_platform == 'linux' and extra == 'cuda'
Requires-Dist: ptyrodactyl[docs,test,notebooks] ; extra == 'dev'
Requires-Dist: black[all]>=25.1.0 ; extra == 'dev'
Requires-Dist: ipykernel>=6.29.5 ; extra == 'dev'
Requires-Dist: isort>=6.0.1 ; extra == 'dev'
Requires-Dist: myst-parser>=4.0.1 ; extra == 'dev'
Requires-Dist: nbsphinx>=0.9.6 ; extra == 'dev'
Requires-Dist: pydata-sphinx-theme>=0.16.1 ; extra == 'dev'
Requires-Dist: ruff>=0.12.9 ; extra == 'dev'
Requires-Dist: sphinx>=8.1.3 ; extra == 'dev'
Requires-Dist: sphinx-rtd-theme>=3.0.2 ; extra == 'dev'
Requires-Dist: sphinxcontrib-napoleon>=0.7 ; extra == 'dev'
Requires-Dist: twine>=6.1.0 ; extra == 'dev'
Requires-Dist: ptyrodactyl[cuda,dev] ; extra == 'dev-cuda'
Requires-Dist: furo>=2025.7.19 ; extra == 'docs'
Requires-Dist: ipykernel>=6.29.5 ; extra == 'docs'
Requires-Dist: myst-parser>=4.0.1 ; extra == 'docs'
Requires-Dist: nbsphinx>=0.9.6 ; extra == 'docs'
Requires-Dist: pydata-sphinx-theme>=0.16.1 ; extra == 'docs'
Requires-Dist: sphinx>=8.1.3 ; extra == 'docs'
Requires-Dist: sphinx-autodoc-typehints>=3.0.1 ; extra == 'docs'
Requires-Dist: sphinx-rtd-theme>=3.0.2 ; extra == 'docs'
Requires-Dist: sphinxcontrib-napoleon>=0.7 ; extra == 'docs'
Requires-Dist: ipywidgets>=8.1.0 ; extra == 'notebooks'
Requires-Dist: ipykernel>=6.29.5 ; extra == 'notebooks'
Requires-Dist: nbconvert>=7.16.6 ; extra == 'notebooks'
Requires-Dist: pytest>=8.3.5 ; extra == 'test'
Requires-Dist: pytest-cov>=4.0.0 ; extra == 'test'
Requires-Dist: pytest-xdist>=3.0.0 ; extra == 'test'
Requires-Dist: chex>=0.1.89 ; extra == 'test'
Maintainer: Debangshu Mukherjee
Maintainer-email: Debangshu Mukherjee <mukherjeed@ornl.gov>
Requires-Python: >=3.11, <3.14
Project-URL: Homepage, https://github.com/debangshu-mukherjee/ptyrodactyl
Provides-Extra: cuda
Provides-Extra: dev
Provides-Extra: dev-cuda
Provides-Extra: docs
Provides-Extra: notebooks
Provides-Extra: test
